odoo/addons/stock_account_valuation_report/README.rst
odoo/addons/stock_account_valuation_report/__init__.py
odoo/addons/stock_account_valuation_report/__manifest__.py
odoo/addons/stock_account_valuation_report/i18n/es.po
odoo/addons/stock_account_valuation_report/i18n/es_MX.po
odoo/addons/stock_account_valuation_report/i18n/fr.po
odoo/addons/stock_account_valuation_report/i18n/sl.po
odoo/addons/stock_account_valuation_report/i18n/stock_account_valuation_report.pot
odoo/addons/stock_account_valuation_report/models/__init__.py
odoo/addons/stock_account_valuation_report/models/account_move_line.py
odoo/addons/stock_account_valuation_report/models/product_product.py
odoo/addons/stock_account_valuation_report/readme/CONTRIBUTORS.rst
odoo/addons/stock_account_valuation_report/readme/DESCRIPTION.rst
odoo/addons/stock_account_valuation_report/security/ir.model.access.csv
odoo/addons/stock_account_valuation_report/static/description/icon.png
odoo/addons/stock_account_valuation_report/static/description/index.html
odoo/addons/stock_account_valuation_report/tests/__init__.py
odoo/addons/stock_account_valuation_report/tests/test_stock_account_valuation_report.py
odoo/addons/stock_account_valuation_report/views/product_product_views.xml
odoo/addons/stock_account_valuation_report/wizards/__init__.py
odoo/addons/stock_account_valuation_report/wizards/stock_valuation_history.py
odoo/addons/stock_account_valuation_report/wizards/stock_valuation_history.xml
odoo14_addon_stock_account_valuation_report-14.0.1.0.1.dist-info/METADATA
odoo14_addon_stock_account_valuation_report-14.0.1.0.1.dist-info/WHEEL
odoo14_addon_stock_account_valuation_report-14.0.1.0.1.dist-info/top_level.txt
odoo14_addon_stock_account_valuation_report-14.0.1.0.1.dist-info/RECORD
